examples/jtag/jtag.v
module jtag (
  input tck, tms, treset,
  output [3:0] outState
);

/* fsm({
  name: 'J',
  condition: 'tms',
  clock: 'tck',
  asyncReset: 'treset',
  ascii: true,
  states: [
    // skewers
    {name: 'testLogicReset', next: {runTest: 0}},
    {name: 'runTest'},

    {name: 'selectDR',  next: {captureDR: 0}},
    {name: 'captureDR', next: {shiftDR:   0}},
    {name: 'shiftDR',   next: {exit1DR:   1}},
    {name: 'exit1DR',   next: {pauseDR:   0}},
    {name: 'pauseDR',   next: {exit2DR:   1}},
    {name: 'exit2DR',   next: {updateDR:  1}},
    'updateDR',

    {name: 'selectIR',  next: {captureIR: 0}},
    {name: 'captureIR', next: {shiftIR:   0}},
    {name: 'shiftIR',   next: {exit1IR:   1}},
    {name: 'exit1IR',   next: {pauseIR:   0}},
    {name: 'pauseIR',   next: {exit2IR:   1}},
    {name: 'exit2IR',   next: {updateIR:  1}},
    'updateIR',

    // bridge
    {name: 'runTest',   next: {selectDR:       1}},
    {name: 'selectDR',  next: {selectIR:       1}},
    {name: 'selectIR',  next: {testLogicReset: 1}},

    // DR
    {name: 'captureDR', next: {exit1DR:  1}},
    {name: 'exit1DR',   next: {updateDR: 1}},
    {name: 'exit2DR',   next: {shiftDR:  0}},
    {name: 'updateDR',  next: {runTest:  0, selectDR: 1}},

    // IR
    {name: 'captureIR', next: {exit1IR:  1}},
    {name: 'exit1IR',   next: {updateIR: 1}},
    {name: 'exit2IR',   next: {shiftIR:  0}},
    {name: 'updateIR',  next: {runTest: 0, selectIR: 1}}
  ]
}) */
// ***** THIS TEXT IS AUTOMATICALLY GENERATED, DO NOT EDIT *****
reg [3:0] J_state, J_next;



// J state enums
wire [3:0] J_testLogicReset = 0;
wire [3:0] J_runTest        = 1;
wire [3:0] J_selectDR       = 2;
wire [3:0] J_captureDR      = 3;
wire [3:0] J_shiftDR        = 4;
wire [3:0] J_exit1DR        = 5;
wire [3:0] J_pauseDR        = 6;
wire [3:0] J_exit2DR        = 7;
wire [3:0] J_updateDR       = 8;
wire [3:0] J_selectIR       = 9;
wire [3:0] J_captureIR      = 10;
wire [3:0] J_shiftIR        = 11;
wire [3:0] J_exit1IR        = 12;
wire [3:0] J_pauseIR        = 13;
wire [3:0] J_exit2IR        = 14;
wire [3:0] J_updateIR       = 15;

// J transition conditions
wire J_testLogicReset_runTest  = (J_state == J_testLogicReset) & (0 == tms);
wire J_runTest_selectDR        = (J_state == J_runTest       ) & (1 == tms);
wire J_selectDR_captureDR      = (J_state == J_selectDR      ) & (0 == tms);
wire J_selectDR_selectIR       = (J_state == J_selectDR      ) & (1 == tms);
wire J_captureDR_shiftDR       = (J_state == J_captureDR     ) & (0 == tms);
wire J_captureDR_exit1DR       = (J_state == J_captureDR     ) & (1 == tms);
wire J_shiftDR_exit1DR         = (J_state == J_shiftDR       ) & (1 == tms);
wire J_exit1DR_pauseDR         = (J_state == J_exit1DR       ) & (0 == tms);
wire J_exit1DR_updateDR        = (J_state == J_exit1DR       ) & (1 == tms);
wire J_pauseDR_exit2DR         = (J_state == J_pauseDR       ) & (1 == tms);
wire J_exit2DR_updateDR        = (J_state == J_exit2DR       ) & (1 == tms);
wire J_exit2DR_shiftDR         = (J_state == J_exit2DR       ) & (0 == tms);
wire J_updateDR_runTest        = (J_state == J_updateDR      ) & (0 == tms);
wire J_updateDR_selectDR       = (J_state == J_updateDR      ) & (1 == tms);
wire J_selectIR_captureIR      = (J_state == J_selectIR      ) & (0 == tms);
wire J_selectIR_testLogicReset = (J_state == J_selectIR      ) & (1 == tms);
wire J_captureIR_shiftIR       = (J_state == J_captureIR     ) & (0 == tms);
wire J_captureIR_exit1IR       = (J_state == J_captureIR     ) & (1 == tms);
wire J_shiftIR_exit1IR         = (J_state == J_shiftIR       ) & (1 == tms);
wire J_exit1IR_pauseIR         = (J_state == J_exit1IR       ) & (0 == tms);
wire J_exit1IR_updateIR        = (J_state == J_exit1IR       ) & (1 == tms);
wire J_pauseIR_exit2IR         = (J_state == J_pauseIR       ) & (1 == tms);
wire J_exit2IR_updateIR        = (J_state == J_exit2IR       ) & (1 == tms);
wire J_exit2IR_shiftIR         = (J_state == J_exit2IR       ) & (0 == tms);
wire J_updateIR_runTest        = (J_state == J_updateIR      ) & (0 == tms);
wire J_updateIR_selectIR       = (J_state == J_updateIR      ) & (1 == tms);

// J state entry conditions
wire J_runTest_onEntry        = (J_testLogicReset_runTest | J_updateDR_runTest | J_updateIR_runTest);
wire J_selectDR_onEntry       = (J_runTest_selectDR | J_updateDR_selectDR);
wire J_captureDR_onEntry      = (J_selectDR_captureDR);
wire J_selectIR_onEntry       = (J_selectDR_selectIR | J_updateIR_selectIR);
wire J_shiftDR_onEntry        = (J_captureDR_shiftDR | J_exit2DR_shiftDR);
wire J_exit1DR_onEntry        = (J_captureDR_exit1DR | J_shiftDR_exit1DR);
wire J_pauseDR_onEntry        = (J_exit1DR_pauseDR);
wire J_updateDR_onEntry       = (J_exit1DR_updateDR | J_exit2DR_updateDR);
wire J_exit2DR_onEntry        = (J_pauseDR_exit2DR);
wire J_captureIR_onEntry      = (J_selectIR_captureIR);
wire J_testLogicReset_onEntry = (J_selectIR_testLogicReset);
wire J_shiftIR_onEntry        = (J_captureIR_shiftIR | J_exit2IR_shiftIR);
wire J_exit1IR_onEntry        = (J_captureIR_exit1IR | J_shiftIR_exit1IR);
wire J_pauseIR_onEntry        = (J_exit1IR_pauseIR);
wire J_updateIR_onEntry       = (J_exit1IR_updateIR | J_exit2IR_updateIR);
wire J_exit2IR_onEntry        = (J_pauseIR_exit2IR);

// J state exit conditions
wire J_testLogicReset_onExit  = (J_testLogicReset_runTest);
wire J_runTest_onExit         = (J_runTest_selectDR);
wire J_selectDR_onExit        = (J_selectDR_captureDR | J_selectDR_selectIR);
wire J_captureDR_onExit       = (J_captureDR_shiftDR | J_captureDR_exit1DR);
wire J_shiftDR_onExit         = (J_shiftDR_exit1DR);
wire J_exit1DR_onExit         = (J_exit1DR_pauseDR | J_exit1DR_updateDR);
wire J_pauseDR_onExit         = (J_pauseDR_exit2DR);
wire J_exit2DR_onExit         = (J_exit2DR_updateDR | J_exit2DR_shiftDR);
wire J_updateDR_onExit        = (J_updateDR_runTest | J_updateDR_selectDR);
wire J_selectIR_onExit        = (J_selectIR_captureIR | J_selectIR_testLogicReset);
wire J_captureIR_onExit       = (J_captureIR_shiftIR | J_captureIR_exit1IR);
wire J_shiftIR_onExit         = (J_shiftIR_exit1IR);
wire J_exit1IR_onExit         = (J_exit1IR_pauseIR | J_exit1IR_updateIR);
wire J_pauseIR_onExit         = (J_pauseIR_exit2IR);
wire J_exit2IR_onExit         = (J_exit2IR_updateIR | J_exit2IR_shiftIR);
wire J_updateIR_onExit        = (J_updateIR_runTest | J_updateIR_selectIR);

// J state self conditions
wire J_testLogicReset_onSelf  = (J_state == J_testLogicReset) & ~J_testLogicReset_onExit;
wire J_runTest_onSelf         = (J_state == J_runTest       ) & ~J_runTest_onExit;
wire J_selectDR_onSelf        = (J_state == J_selectDR      ) & ~J_selectDR_onExit;
wire J_captureDR_onSelf       = (J_state == J_captureDR     ) & ~J_captureDR_onExit;
wire J_shiftDR_onSelf         = (J_state == J_shiftDR       ) & ~J_shiftDR_onExit;
wire J_exit1DR_onSelf         = (J_state == J_exit1DR       ) & ~J_exit1DR_onExit;
wire J_pauseDR_onSelf         = (J_state == J_pauseDR       ) & ~J_pauseDR_onExit;
wire J_exit2DR_onSelf         = (J_state == J_exit2DR       ) & ~J_exit2DR_onExit;
wire J_updateDR_onSelf        = (J_state == J_updateDR      ) & ~J_updateDR_onExit;
wire J_selectIR_onSelf        = (J_state == J_selectIR      ) & ~J_selectIR_onExit;
wire J_captureIR_onSelf       = (J_state == J_captureIR     ) & ~J_captureIR_onExit;
wire J_shiftIR_onSelf         = (J_state == J_shiftIR       ) & ~J_shiftIR_onExit;
wire J_exit1IR_onSelf         = (J_state == J_exit1IR       ) & ~J_exit1IR_onExit;
wire J_pauseIR_onSelf         = (J_state == J_pauseIR       ) & ~J_pauseIR_onExit;
wire J_exit2IR_onSelf         = (J_state == J_exit2IR       ) & ~J_exit2IR_onExit;
wire J_updateIR_onSelf        = (J_state == J_updateIR      ) & ~J_updateIR_onExit;

// J next state select
always @(*) begin : J_next_select
  case (1'b1)
    J_testLogicReset_runTest  : J_next = J_runTest;
    J_runTest_selectDR        : J_next = J_selectDR;
    J_selectDR_captureDR      : J_next = J_captureDR;
    J_selectDR_selectIR       : J_next = J_selectIR;
    J_captureDR_shiftDR       : J_next = J_shiftDR;
    J_captureDR_exit1DR       : J_next = J_exit1DR;
    J_shiftDR_exit1DR         : J_next = J_exit1DR;
    J_exit1DR_pauseDR         : J_next = J_pauseDR;
    J_exit1DR_updateDR        : J_next = J_updateDR;
    J_pauseDR_exit2DR         : J_next = J_exit2DR;
    J_exit2DR_updateDR        : J_next = J_updateDR;
    J_exit2DR_shiftDR         : J_next = J_shiftDR;
    J_updateDR_runTest        : J_next = J_runTest;
    J_updateDR_selectDR       : J_next = J_selectDR;
    J_selectIR_captureIR      : J_next = J_captureIR;
    J_selectIR_testLogicReset : J_next = J_testLogicReset;
    J_captureIR_shiftIR       : J_next = J_shiftIR;
    J_captureIR_exit1IR       : J_next = J_exit1IR;
    J_shiftIR_exit1IR         : J_next = J_exit1IR;
    J_exit1IR_pauseIR         : J_next = J_pauseIR;
    J_exit1IR_updateIR        : J_next = J_updateIR;
    J_pauseIR_exit2IR         : J_next = J_exit2IR;
    J_exit2IR_updateIR        : J_next = J_updateIR;
    J_exit2IR_shiftIR         : J_next = J_shiftIR;
    J_updateIR_runTest        : J_next = J_runTest;
    J_updateIR_selectIR       : J_next = J_selectIR;
    default                   : J_next = J_state;
  endcase
end

always @(posedge tck or posedge treset)
  if (treset) J_state <= J_testLogicReset;
  else        J_state <= J_next;

reg [111:0] J_state_ascii;
always @(*)
  case ({J_state})
    J_testLogicReset : J_state_ascii = "testLogicReset";
    J_runTest        : J_state_ascii = "runTest       ";
    J_selectDR       : J_state_ascii = "selectDR      ";
    J_captureDR      : J_state_ascii = "captureDR     ";
    J_shiftDR        : J_state_ascii = "shiftDR       ";
    J_exit1DR        : J_state_ascii = "exit1DR       ";
    J_pauseDR        : J_state_ascii = "pauseDR       ";
    J_exit2DR        : J_state_ascii = "exit2DR       ";
    J_updateDR       : J_state_ascii = "updateDR      ";
    J_selectIR       : J_state_ascii = "selectIR      ";
    J_captureIR      : J_state_ascii = "captureIR     ";
    J_shiftIR        : J_state_ascii = "shiftIR       ";
    J_exit1IR        : J_state_ascii = "exit1IR       ";
    J_pauseIR        : J_state_ascii = "pauseIR       ";
    J_exit2IR        : J_state_ascii = "exit2IR       ";
    J_updateIR       : J_state_ascii = "updateIR      ";
    default          : J_state_ascii = "%Error        ";
  endcase

// ***** END OF AUTOMATICALLY GENERATED TEXT, DO NOT EDIT *****
/* fin */

assign outState = J_state;

endmodule

jtag/tb.v
`timescale 10ns/1ns

module tb;
  reg treset = 1;
  initial begin
     $dumpfile("jtag.vcd");
     $dumpvars(0, tb);
     # 3 treset = 0;
     # 1000 $finish;
  end

  reg [31:0] seed = 12;
  reg tms = 0;
  always #1 tms = $random(seed);

  reg tck = 1;
  always #0.5 tck = !tck;

  wire [3:0] jtagState;
  jtag u0 (.outState(jtagState), .tck(tck), .tms(tms), .treset(treset));

endmodule

jtag/jtag.vcd
$date
	Thu Feb 12 23:38:16 2026
$end
$version
	Icarus Verilog
$end
$timescale
	1ns
$end
$scope module tb $end
$var wire 4 ! jtagState [3:0] $end
$var reg 32 " seed [31:0] $end
$var reg 1 # tck $end
$var reg 1 $ tms $end
$var reg 1 % treset $end
$scope module u0 $end
$var wire 4 & J_captureDR [3:0] $end
$var wire 1 ' J_captureDR_exit1DR $end
$var wire 1 ( J_captureDR_onEntry $end
$var wire 1 ) J_captureDR_onExit $end
$var wire 1 * J_captureDR_onSelf $end
$var wire 1 + J_captureDR_shiftDR $end
$var wire 4 , J_captureIR [3:0] $end
$var wire 1 - J_captureIR_exit1IR $end
$var wire 1 . J_captureIR_onEntry $end
$var wire 1 / J_captureIR_onExit $end
$var wire 1 0 J_captureIR_onSelf $end
$var wire 1 1 J_captureIR_shiftIR $end
$var wire 4 2 J_exit1DR [3:0] $end
$var wire 1 3 J_exit1DR_onEntry $end
$var wire 1 4 J_exit1DR_onExit $end
$var wire 1 5 J_exit1DR_onSelf $end
$var wire 1 6 J_exit1DR_pauseDR $end
$var wire 1 7 J_exit1DR_updateDR $end
$var wire 4 8 J_exit1IR [3:0] $end
$var wire 1 9 J_exit1IR_onEntry $end
$var wire 1 : J_exit1IR_onExit $end
$var wire 1 ; J_exit1IR_onSelf $end
$var wire 1 < J_exit1IR_pauseIR $end
$var wire 1 = J_exit1IR_updateIR $end
$var wire 4 > J_exit2DR [3:0] $end
$var wire 1 ? J_exit2DR_onEntry $end
$var wire 1 @ J_exit2DR_onExit $end
$var wire 1 A J_exit2DR_onSelf $end
$var wire 1 B J_exit2DR_shiftDR $end
$var wire 1 C J_exit2DR_updateDR $end
$var wire 4 D J_exit2IR [3:0] $end
$var wire 1 E J_exit2IR_onEntry $end
$var wire 1 F J_exit2IR_onExit $end
$var wire 1 G J_exit2IR_onSelf $end
$var wire 1 H J_exit2IR_shiftIR $end
$var wire 1 I J_exit2IR_updateIR $end
$var wire 4 J J_pauseDR [3:0] $end
$var wire 1 K J_pauseDR_exit2DR $end
$var wire 1 L J_pauseDR_onEntry $end
$var wire 1 M J_pauseDR_onExit $end
$var wire 1 N J_pauseDR_onSelf $end
$var wire 4 O J_pauseIR [3:0] $end
$var wire 1 P J_pauseIR_exit2IR $end
$var wire 1 Q J_pauseIR_onEntry $end
$var wire 1 R J_pauseIR_onExit $end
$var wire 1 S J_pauseIR_onSelf $end
$var wire 4 T J_runTest [3:0] $end
$var wire 1 U J_runTest_onEntry $end
$var wire 1 V J_runTest_onExit $end
$var wire 1 W J_runTest_onSelf $end
$var wire 1 X J_runTest_selectDR $end
$var wire 4 Y J_selectDR [3:0] $end
$var wire 1 Z J_selectDR_captureDR $end
$var wire 1 [ J_selectDR_onEntry $end
$var wire 1 \ J_selectDR_onExit $end
$var wire 1 ] J_selectDR_onSelf $end
$var wire 1 ^ J_selectDR_selectIR $end
$var wire 4 _ J_selectIR [3:0] $end
$var wire 1 ` J_selectIR_captureIR $end
$var wire 1 a J_selectIR_onEntry $end
$var wire 1 b J_selectIR_onExit $end
$var wire 1 c J_selectIR_onSelf $end
$var wire 1 d J_selectIR_testLogicReset $end
$var wire 4 e J_shiftDR [3:0] $end
$var wire 1 f J_shiftDR_exit1DR $end
$var wire 1 g J_shiftDR_onEntry $end
$var wire 1 h J_shiftDR_onExit $end
$var wire 1 i J_shiftDR_onSelf $end
$var wire 4 j J_shiftIR [3:0] $end
$var wire 1 k J_shiftIR_exit1IR $end
$var wire 1 l J_shiftIR_onEntry $end
$var wire 1 m J_shiftIR_onExit $end
$var wire 1 n J_shiftIR_onSelf $end
$var wire 4 o J_testLogicReset [3:0] $end
$var wire 1 p J_testLogicReset_onEntry $end
$var wire 1 q J_testLogicReset_onExit $end
$var wire 1 r J_testLogicReset_onSelf $end
$var wire 1 s J_testLogicReset_runTest $end
$var wire 4 t J_updateDR [3:0] $end
$var wire 1 u J_updateDR_onEntry $end
$var wire 1 v J_updateDR_onExit $end
$var wire 1 w J_updateDR_onSelf $end
$var wire 1 x J_updateDR_runTest $end
$var wire 1 y J_updateDR_selectDR $end
$var wire 4 z J_updateIR [3:0] $end
$var wire 1 { J_updateIR_onEntry $end
$var wire 1 | J_updateIR_onExit $end
$var wire 1 } J_updateIR_onSelf $end
$var wire 1 ~ J_updateIR_runTest $end
$var wire 1 !" J_updateIR_selectIR $end
$var wire 4 "" outState [3:0] $end
$var wire 1 # tck $end
$var wire 1 $ tms $end
$var wire 1 % treset $end
$var reg 4 #" J_next [3:0] $end
$var reg 4 $" J_state [3:0] $end
$var reg 112 %" J_state_ascii [111:0] $end
$scope begin J_next_select $end
$upscope $end
$upscope $end
$upscope $end
$enddefinitions $end
$comment Show the parameter values. $end
$dumpall
$end
#0
$dumpvars
b111010001100101011100110111010001001100011011110110011101101001011000110101001001100101011100110110010101110100 %"
b0 $"
b1 #"
b0 ""
0!"
0~
0}
0|
0{
b1111 z
0y
0x
0w
0v
0u
b1000 t
1s
0r
1q
0p
b0 o
0n
0m
0l
0k
b1011 j
0i
0h
0g
0f
b100 e
0d
0c
0b
0a
0`
b1001 _
0^
0]
0\
0[
0Z
b10 Y
0X
0W
0V
1U
b1 T
0S
0R
0Q
0P
b1101 O
0N
0M
0L
0K
b110 J
0I
0H
0G
0F
0E
b1110 D
0C
0B
0A
0@
0?
b111 >
0=
0<
0;
0:
09
b1100 8
07
06
05
04
03
b101 2
01
00
0/
0.
0-
b1010 ,
0+
0*
0)
0(
0'
b11 &
1%
0$
1#
b1100 "
b0 !
$end
#5
0#
#10
1#
b11001010010110011101 "
#15
0#
#20
1#
b1010100001001101001011110111010 "
#25
0#
#30
0U
b111001001110101011011100101010001100101011100110111010000100000001000000010000000100000001000000010000000100000 %"
0q
0s
1W
b1 !
b1 ""
b1 $"
1#
b11110000010101011111000111110011 "
0%
#35
0#
#40
1#
b11000100000011110001011010011000 "
#45
0#
#50
0W
1[
b10 #"
1V
1X
1#
1$
b11011010110100101100111110111001 "
#55
0#
#60
1\
b111001101100101011011000110010101100011011101000100010001010010001000000010000000100000001000000010000000100000 %"
1(
1Z
0]
b10 !
b10 ""
b10 $"
0W
0[
b11 #"
0V
0X
1#
0$
b10111111000101011011110000100110 "
#65
0#
#70
0\
1g
1)
b110001101100001011100000111010001110101011100100110010101000100010100100010000000100000001000000010000000100000 %"
b100 #"
0(
0Z
1+
0*
b11 !
b11 ""
b11 $"
1#
b11011011000110111001100001101111 "
#75
0#
#80
0g
0)
b111001101101000011010010110011001110100010001000101001000100000001000000010000000100000001000000010000000100000 %"
0+
1i
b100 !
b100 ""
b100 $"
1#
b1110100010001011011001111100100 "
#85
0#
#90
0i
13
b101 #"
1h
1f
1#
1$
b1011001110101111010000110010101 "
#95
0#
#100
14
b110010101111000011010010111010000110001010001000101001000100000001000000010000000100000001000000010000000100000 %"
1L
16
05
b101 !
b101 ""
b101 $"
0i
03
b110 #"
0h
0f
1#
0$
b10000110011101011111010101010010 "
#105
0#
#110
04
b111000001100001011101010111001101100101010001000101001000100000001000000010000000100000001000000010000000100000 %"
0L
06
1N
b110 !
b110 ""
b110 $"
1#
b10011111001111001001110010101011 "
#115
0#
#120
1#
b110100001010010010001111110000 "
#125
0#
#130
0N
b111 #"
1?
1M
1K
1#
1$
b11111111101101001111011100110001 "
#135
0#
#140
1u
1@
b110010101111000011010010111010000110010010001000101001000100000001000000010000000100000001000000010000000100000 %"
b1000 #"
0?
0M
0K
1C
0A
b111 !
b111 ""
b111 $"
1#
b11101011101010000110111100111110 "
#145
0#
#150
0u
0@
1[
1v
b111010101110000011001000110000101110100011001010100010001010010001000000010000000100000001000000010000000100000 %"
b10 #"
0C
1y
0w
b1000 !
b1000 ""
b1000 $"
1#
b10110010110001010011101010100111 "
#155
0#
#160
1a
1\
0[
0v
b111001101100101011011000110010101100011011101000100010001010010001000000010000000100000001000000010000000100000 %"
b1001 #"
1^
0y
0]
b10 !
b10 ""
b10 $"
1#
b1100110100100010111001010111100 "
#165
0#
#170
0\
1b
b111001101100101011011000110010101100011011101000100100101010010001000000010000000100000001000000010000000100000 %"
1.
1`
0c
b1001 !
b1001 ""
b1001 $"
0a
b1010 #"
0(
0Z
0^
1#
0$
b11111000000010000110110010001101 "
#175
0#
#180
0b
19
1/
b110001101100001011100000111010001110101011100100110010101001001010100100010000000100000001000000010000000100000 %"
1-
00
b1010 !
b1010 ""
b1010 $"
b1100 #"
0.
0`
0p
0d
1#
1$
b1111000110011110001010111101010 "
#185
0#
#190
09
0/
1{
1:
b110010101111000011010010111010000110001010010010101001000100000001000000010000000100000001000000010000000100000 %"
b1111 #"
0-
1=
0;
b1100 !
b1100 ""
b1100 $"
1#
b1010111110110110110111001100011 "
#195
0#
#200
0{
0:
1a
1|
b111010101110000011001000110000101110100011001010100100101010010001000000010000000100000001000000010000000100000 %"
b1001 #"
0=
1!"
0}
b1111 !
b1111 ""
b1111 $"
1#
b11101101101101010110110001001000 "
#205
0#
#210
1b
0|
b111001101100101011011000110010101100011011101000100100101010010001000000010000000100000001000000010000000100000 %"
1.
1`
0c
b1001 !
b1001 ""
b1001 $"
0U
0a
b1010 #"
0~
0!"
1#
0$
b11111101000011110101110110101001 "
#215
0#
#220
0b
19
1/
b110001101100001011100000111010001110101011100100110010101001001010100100010000000100000001000000010000000100000 %"
1-
00
b1010 !
b1010 ""
b1010 $"
b1100 #"
0.
0`
0p
0d
1#
1$
b11001010101110001001010101010110 "
#225
0#
#230
09
0/
1{
1:
b110010101111000011010010111010000110001010010010101001000100000001000000010000000100000001000000010000000100000 %"
b1111 #"
0-
1=
0;
b1100 !
b1100 ""
b1100 $"
1#
b1001010101110101111001111011111 "
#235
0#
#240
0{
0:
1a
1|
b111010101110000011001000110000101110100011001010100100101010010001000000010000000100000001000000010000000100000 %"
b1001 #"
0=
1!"
0}
b1111 !
b1111 ""
b1111 $"
1#
b1001001111101101001110010010100 "
#245
0#
#250
1b
0|
b111001101100101011011000110010101100011011101000100100101010010001000000010000000100000001000000010000000100000 %"
1.
1`
0c
b1001 !
b1001 ""
b1001 $"
0U
0a
b1010 #"
0~
0!"
1#
0$
b1011101000000101110011010000101 "
#255
0#
#260
0b
19
1/
b110001101100001011100000111010001110101011100100110010101001001010100100010000000100000001000000010000000100000 %"
1-
00
b1010 !
b1010 ""
b1010 $"
b1100 #"
0.
0`
0p
0d
1#
1$
b10000111100011000101100110000010 "
#265
0#
#270
0/
1:
b110010101111000011010010111010000110001010010010101001000100000001000000010000000100000001000000010000000100000 %"
1Q
1<
0;
b1100 !
b1100 ""
b1100 $"
0l
09
b1101 #"
01
0-
1#
0$
b101011100010100011100011011 "
#275
0#
#280
0:
b111000001100001011101010111001101100101010010010101001000100000001000000010000000100000001000000010000000100000 %"
0Q
0<
1S
b1101 !
b1101 ""
b1101 $"
1#
b1100011011011010100111110100000 "
#285
0#
#290
1#
b1111011001100111110001100100001 "
#295
0#
#300
1#
b101110001101101000111001101110 "
#305
0#
#310
1#
b1010101010110011010010000010111 "
#315
0#
#320
1#
b10001010001101001001000101101100 "
#325
0#
#330
0S
b1110 #"
1E
1R
1P
1#
1$
b11101000111001101110111101111101 "
#335
0#
#340
1{
1F
b110010101111000011010010111010000110010010010010101001000100000001000000010000000100000001000000010000000100000 %"
b1111 #"
0E
0R
0P
1I
0G
b1110 !
b1110 ""
b1110 $"
1#
b101010100101000010000000011010 "
#345
0#
#350
0F
1U
1|
b111010101110000011001000110000101110100011001010100100101010010001000000010000000100000001000000010000000100000 %"
1~
0}
b1111 !
b1111 ""
b1111 $"
0{
0l
b1 #"
0I
0H
1#
0$
b10111110010110010000011011010011 "
#355
0#
#360
0U
0|
b111001001110101011011100101010001100101011100110111010000100000001000000010000000100000001000000010000000100000 %"
0~
1W
b1 !
b1 ""
b1 $"
1#
b11111001011101100010110111111000 "
#365
0#
#370
0W
1[
b10 #"
1V
1X
1#
1$
b11110001111100000110011110011001 "
#375
0#
#380
1\
b111001101100101011011000110010101100011011101000100010001010010001000000010000000100000001000000010000000100000 %"
1(
1Z
0]
b10 !
b10 ""
b10 $"
0W
0[
b11 #"
0V
0X
1#
0$
b1011010010111101011101010000110 "
#385
0#
#390
0\
13
1)
b110001101100001011100000111010001110101011100100110010101000100010100100010000000100000001000000010000000100000 %"
1'
0*
b11 !
b11 ""
b11 $"
0a
b101 #"
0(
0Z
0^
1#
1$
b11100111110110100010101101001111 "
#395
0#
#400
0)
14
b110010101111000011010010111010000110001010001000101001000100000001000000010000000100000001000000010000000100000 %"
1L
16
05
b101 !
b101 ""
b101 $"
0g
03
b110 #"
0+
0'
1#
0$
b11101001001101101011000101000100 "
#405
0#
#410
04
b111000001100001011101010111001101100101010001000101001000100000001000000010000000100000001000000010000000100000 %"
0L
06
1N
b110 !
b110 ""
b110 $"
1#
b111001000100000110011101110101 "
#415
0#
#420
0N
b111 #"
1?
1M
1K
1#
1$
b11101110110110001100100110110010 "
#425
0#
#430
1u
1@
b110010101111000011010010111010000110010010001000101001000100000001000000010000000100000001000000010000000100000 %"
b1000 #"
0?
0M
0K
1C
0A
b111 !
b111 ""
b111 $"
1#
b1111100010011000110110001011 "
#435
0#
#440
0u
0@
1[
1v
b111010101110000011001000110000101110100011001010100010001010010001000000010000000100000001000000010000000100000 %"
b10 #"
0C
1y
0w
b1000 !
b1000 ""
b1000 $"
1#
b11111010111000010110011101010000 "
#445
0#
#450
1\
0v
b111001101100101011011000110010101100011011101000100010001010010001000000010000000100000001000000010000000100000 %"
1(
1Z
0]
b10 !
b10 ""
b10 $"
0U
0[
b11 #"
0x
0y
1#
0$
b11000000000011101100101100010001 "
#455
0#
#460
0\
1g
1)
b110001101100001011100000111010001110101011100100110010101000100010100100010000000100000001000000010000000100000 %"
b100 #"
0(
0Z
1+
0*
b11 !
b11 ""
b11 $"
1#
b1010111001110010111100110011110 "
#465
0#
#470
0)
b111001101101000011010010110011001110100010001000101001000100000001000000010000000100000001000000010000000100000 %"
1h
1f
0i
b100 !
b100 ""
b100 $"
0g
13
b101 #"
0+
0'
1#
1$
b111101110100010110100110000111 "
#475
0#
#480
03
1u
14
b110010101111000011010010111010000110001010001000101001000100000001000000010000000100000001000000010000000100000 %"
b1000 #"
0h
0f
17
05
b101 !
b101 ""
b101 $"
1#
b10001100100101000101110000011100 "
#485
0#
#490
0u
04
1[
1v
b111010101110000011001000110000101110100011001010100010001010010001000000010000000100000001000000010000000100000 %"
b10 #"
07
1y
0w
b1000 !
b1000 ""
b1000 $"
1#
b1110111100101110010111001101101 "
#495
0#
#500
1a
1\
0[
0v
b111001101100101011011000110010101100011011101000100010001010010001000000010000000100000001000000010000000100000 %"
b1001 #"
1^
0y
0]
b10 !
b10 ""
b10 $"
1#
b10011111110110001011011001001010 "
#505
0#
#510
0\
1b
b111001101100101011011000110010101100011011101000100100101010010001000000010000000100000001000000010000000100000 %"
1.
1`
0c
b1001 !
b1001 ""
b1001 $"
0a
b1010 #"
0(
0Z
0^
1#
0$
b10111000000101011011101101000011 "
#515
0#
#520
0b
1l
1/
b110001101100001011100000111010001110101011100100110010101001001010100100010000000100000001000000010000000100000 %"
b1011 #"
0.
0`
11
00
b1010 !
b1010 ""
b1010 $"
1#
b111111001011000101101110101000 "
#525
0#
#530
0/
b111001101101000011010010110011001110100010010010101001000100000001000000010000000100000001000000010000000100000 %"
1m
1k
0n
b1011 !
b1011 ""
b1011 $"
0l
19
b1100 #"
01
0-
1#
1$
b110010110101001110110110001001 "
#535
0#
#540
1:
b110010101111000011010010111010000110001010010010101001000100000001000000010000000100000001000000010000000100000 %"
1Q
1<
0;
b1100 !
b1100 ""
b1100 $"
0n
09
b1101 #"
0m
0k
1#
0$
b1110010000110110010101110110110 "
#545
0#
#550
0:
b111000001100001011101010111001101100101010010010101001000100000001000000010000000100000001000000010000000100000 %"
1E
1R
1P
0S
b1101 !
b1101 ""
b1101 $"
0{
b1110 #"
0Q
0<
0=
1#
1$
b11101100101100000011111010111111 "
#555
0#
#560
1l
1F
b110010101111000011010010111010000110010010010010101001000100000001000000010000000100000001000000010000000100000 %"
1H
0G
b1110 !
b1110 ""
b1110 $"
0S
b1011 #"
0E
0R
0P
1#
0$
b10111011000100001111000111110100 "
#565
0#
#570
19
0F
b111001101101000011010010110011001110100010010010101001000100000001000000010000000100000001000000010000000100000 %"
1m
1k
0n
b1011 !
b1011 ""
b1011 $"
0{
0l
b1100 #"
0I
0H
1#
1$
b10011010110011110010010001100101 "
#575
0#
#580
1:
b110010101111000011010010111010000110001010010010101001000100000001000000010000000100000001000000010000000100000 %"
1Q
1<
0;
b1100 !
b1100 ""
b1100 $"
0n
09
b1101 #"
0m
0k
1#
0$
b10100001000111100100010111100010 "
#585
0#
#590
0:
b111000001100001011101010111001101100101010010010101001000100000001000000010000000100000001000000010000000100000 %"
1E
1R
1P
0S
b1101 !
b1101 ""
b1101 $"
0{
b1110 #"
0Q
0<
0=
1#
1$
b11010100101011000110111111111011 "
#595
0#
#600
1{
1F
b110010101111000011010010111010000110010010010010101001000100000001000000010000000100000001000000010000000100000 %"
b1111 #"
0E
0R
0P
1I
0G
b1110 !
b1110 ""
b1110 $"
1#
b1111111110000000110101100000000 "
#605
0#
#610
0{
0F
1a
1|
b111010101110000011001000110000101110100011001010100100101010010001000000010000000100000001000000010000000100000 %"
b1001 #"
0I
1!"
0}
b1111 !
b1111 ""
b1111 $"
1#
b1111101100001001010111100000001 "
#615
0#
#620
1b
0|
b111001101100101011011000110010101100011011101000100100101010010001000000010000000100000001000000010000000100000 %"
1.
1`
0c
b1001 !
b1001 ""
b1001 $"
0U
0a
b1010 #"
0~
0!"
1#
0$
b11101111001001000011000011001110 "
#625
0#
#630
0b
1l
1/
b110001101100001011100000111010001110101011100100110010101001001010100100010000000100000001000000010000000100000 %"
b1011 #"
0.
0`
11
00
b1010 !
b1010 ""
b1010 $"
1#
b10000111010000111000101011110111 "
#635
0#
#640
0l
0/
b111001101101000011010010110011001110100010010010101001000100000001000000010000000100000001000000010000000100000 %"
01
1n
b1011 !
b1011 ""
b1011 $"
1#
b1001010000110111101001011001100 "
#645
0#
#650
0n
19
b1100 #"
1m
1k
1#
1$
b10010100110010000010100101011101 "
#655
0#
