examples/random/tb.v
`timescale 10ns/1ns

module tb;
  reg rstn = 0;
  initial begin
     $dumpfile("random.vcd");
     $dumpvars(0, tb);
     # 8 rstn = 1;
     # 32 $finish;
  end

  reg clk = 1;
  always #0.5 clk = !clk;

  reg [31:0] seed = 42;
  reg [7:0] value;
  always #1 value = $random(seed);

endmodule

examples/random/random.vcd
$date
	Mon Jan 22 17:24:55 2024
$end
$version
	Icarus Verilog
$end
$timescale
	1ns
$end
$scope module tb $end
$var reg 1 ! clk $end
$var reg 1 " rstn $end
$var reg 32 # seed [31:0] $end
$var reg 8 $ value [7:0] $end
$upscope $end
$enddefinitions $end
#0
$dumpvars
bx $
b101010 #
0"
1!
$end
#5
0!
#10
1!
b0 $
b1011000100001110100011 #
#15
0!
#20
1!
b1001101 $
b10100110100001000111000010001000 #
#25
0!
#30
1!
b100 $
b10000010010011010000010011101001 #
#35
0!
#40
1!
b10001011 $
b1000101110101011100001110010110 #
#45
0!
#50
1!
b10101 $
b10001010101100100011110100011111 #
#55
0!
#60
1!
b10110101 $
b1011010111101001000010011010100 #
#65
0!
#70
1!
b10001010 $
b11000101011000010010000111000101 #
#75
0!
#80
1!
b111110 $
b11111010001000000101111000010 #
1"
#85
0!
#90
1!
b10011 $
b10001001110110000100010001011011 #
#95
0!
#100
1!
b1000100 $
b10100010000000100101101111100000 #
#105
0!
#110
1!
b1101100 $
b110110011011011111001001100001 #
#115
0!
#120
1!
b111011 $
b11101101110110000010010101110 #
#125
0!
#130
1!
b10100101 $
b1010010101011011001010101010111 #
#135
0!
#140
1!
b110101 $
b10011010111011010000000110101100 #
#145
0!
#150
1!
b11010100011000001001010111101 #
#155
0!
#160
1!
b11100011 $
b1110001110110111001101001011010 #
#165
0!
#170
1!
b11011100 $
b11101110000010110010110000010011 #
#175
0!
#180
1!
b10111000 $
b1011100010000100100001000111000 #
#185
0!
#190
1!
b1 $
b10000000101000111101111011011001 #
#195
0!
#200
1!
b1101000 $
b110100011000110111100011000110 #
#205
0!
#210
1!
b11110011 $
b1111001100011111100010010001111 #
#215
0!
#220
1!
b11010011 $
b1101001101010101010100110000100 #
#225
0!
#230
1!
b11100011 $
b11110001110010010111001010110101 #
#235
0!
#240
1!
b10010111 $
b1001011110110010000101111110010 #
#245
0!
#250
1!
b10011100 $
b11001110010110111101101011001011 #
#255
0!
#260
1!
b10001000 $
b11000100011101011000001110010000 #
#265
0!
#270
1!
b10011010 $
b11001101010110001010101001010001 #
#275
0!
#280
1!
b110101 $
b10011010111101110111111111011110 #
#285
0!
#290
1!
b1010011 $
b101001100011011010101011000111 #
#295
0!
#300
1!
b1000101 $
b100010111001001101110001011100 #
#305
0!
#310
1!
b11011001 $
b1101100110100010010000110101101 #
#315
0!
#320
1!
b11000111 $
b11100011110110101100000010001010 #
#325
0!
#330
1!
b10100100 $
b1010010011111010011000010000011 #
#335
0!
#340
1!
b110100 $
b10011010001110010111111111101000 #
#345
0!
#350
1!
b11010110 $
b11101011011100100011010011001001 #
#355
0!
#360
1!
b10111 $
b10001011111010110111100111110110 #
#365
0!
#370
1!
b11110101 $
b1111010101110000010011111111111 #
#375
0!
#380
1!
b10001110 $
b11000111011111101111101000110100 #
#385
0!
#390
1!
b1011011 $
b101101100101101111111110100101 #
#395
0!
#400
1!
b101100100010110001100000100010 #
