examples/random/tb.v
`timescale 10ns/10ns

module tb;
  reg rstn = 0;
  initial begin
     $dumpfile("random.vcd");
     $dumpvars(0, tb);
     # 8 rstn = 1;
     # 32 $finish;
  end

  reg clk = 1;
  always #1 clk = !clk;

  reg [31:0] seed = 42;
  reg [7:0] value;
  always #2 value = $random(seed);

endmodule

examples/random/random.vcd
$date
	Mon Jan 22 16:58:16 2024
$end
$version
	Icarus Verilog
$end
$timescale
	10ns
$end
$scope module tb $end
$var reg 1 ! clk $end
$var reg 1 " rstn $end
$var reg 32 # seed [31:0] $end
$var reg 8 $ value [7:0] $end
$upscope $end
$enddefinitions $end
#0
$dumpvars
bx $
b101010 #
0"
1!
$end
#1
0!
#2
1!
b0 $
b1011000100001110100011 #
#3
0!
#4
1!
b1001101 $
b10100110100001000111000010001000 #
#5
0!
#6
1!
b100 $
b10000010010011010000010011101001 #
#7
0!
#8
1!
b10001011 $
b1000101110101011100001110010110 #
1"
#9
0!
#10
1!
b10101 $
b10001010101100100011110100011111 #
#11
0!
#12
1!
b10110101 $
b1011010111101001000010011010100 #
#13
0!
#14
1!
b10001010 $
b11000101011000010010000111000101 #
#15
0!
#16
1!
b111110 $
b11111010001000000101111000010 #
#17
0!
#18
1!
b10011 $
b10001001110110000100010001011011 #
#19
0!
#20
1!
b1000100 $
b10100010000000100101101111100000 #
#21
0!
#22
1!
b1101100 $
b110110011011011111001001100001 #
#23
0!
#24
1!
b111011 $
b11101101110110000010010101110 #
#25
0!
#26
1!
b10100101 $
b1010010101011011001010101010111 #
#27
0!
#28
1!
b110101 $
b10011010111011010000000110101100 #
#29
0!
#30
1!
b11010100011000001001010111101 #
#31
0!
#32
1!
b11100011 $
b1110001110110111001101001011010 #
#33
0!
#34
1!
b11011100 $
b11101110000010110010110000010011 #
#35
0!
#36
1!
b10111000 $
b1011100010000100100001000111000 #
#37
0!
#38
1!
b1 $
b10000000101000111101111011011001 #
#39
0!
#40
1!
b110100011000110111100011000110 #
