examples/random/counter.v
module counter (
  output reg [7:0] out,
  input clk, rstn
);

always @(posedge clk or negedge rstn)
  if (!rstn)
    out <= 8'b0;
  else
    out <= out + 1;

endmodule

examples/random/tb.v
`timescale 10ns/1ns

module tb;
  reg rstn = 0;
  initial begin
     $dumpfile("random.vcd");
     $dumpvars(0, tb);
     # 8 rstn = 1;
     # 32 $finish;
  end

  reg clk = 1;
  always #0.5 clk = !clk;

  wire [7:0] value;
  counter u0 (value, clk, rstn);

  reg [31:0] seed = 2;
  reg [7:0] rnd;
  always #1 rnd = $random(seed);

endmodule

examples/random/random.vcd
$date
	Mon Jan 22 18:45:53 2024
$end
$version
	Icarus Verilog
$end
$timescale
	1ns
$end
$scope module tb $end
$var wire 8 ! value [7:0] $end
$var reg 1 " clk $end
$var reg 8 # rnd [7:0] $end
$var reg 1 $ rstn $end
$var reg 32 % seed [31:0] $end
$scope module u0 $end
$var wire 1 " clk $end
$var wire 1 $ rstn $end
$var reg 8 & out [7:0] $end
$upscope $end
$upscope $end
$enddefinitions $end
#0
$dumpvars
b0 &
b10 %
0$
bx #
1"
b0 !
$end
#5
0"
#10
1"
b0 #
b100001101110011011 %
#15
0"
#20
1"
b1110001 #
b111000101100011111101000100000 %
#25
0"
#30
1"
b11010100 #
b1101010010110001110101110100001 %
#35
0"
#40
1"
b110001 #
b10011000110011001101110011101110 %
#45
0"
#50
1"
b1000000 #
b10100000001100110000000010010111 %
#55
0"
#60
1"
b11000000 #
b11100000011101100010001111101100 %
#65
0"
#70
1"
b11000100 #
b11100010010110011011111111111101 %
#75
0"
#80
b1 !
b1 &
1"
b100001 #
b10010000100110111001011010011010 %
1$
#85
0"
#90
b10 !
b10 &
1"
b10010011 #
b1001001110101110110101101010011 %
#95
0"
#100
b11 !
b11 &
1"
b11111010 #
b1111101010001110010100001111000 %
#105
0"
#110
b100 !
b100 &
1"
b101111 #
b10111100000011000000000011001 %
#115
0"
#120
b101 !
b101 &
1"
b11001100 #
b11100110010011011101100100000110 %
#125
0"
#130
b110 !
b110 &
1"
b1110010 #
b111001011000100001011111001111 %
#135
0"
#140
b111 !
b111 &
1"
b1101 #
b110100100011001001111000100 %
#145
0"
#150
b1000 !
b1000 &
1"
b1110101 #
b111010110110000100011111110101 %
#155
0"
#160
b1001 !
b1001 &
1"
b11000101 #
b1100010110011100001000000110010 %
#165
0"
#170
b1010 !
b1010 &
1"
b1001100 #
b10100110000001111000001000001011 %
#175
0"
#180
b1011 !
b1011 &
1"
b10101111 #
b11010111101010001011000111010000 %
#185
0"
#190
b1100 !
b1100 &
1"
b11101001 #
b11110100111011011111001110010001 %
#195
0"
#200
b1101 !
b1101 &
1"
b1010110 #
b101011011110110110100000011110 %
#205
0"
#210
b1110 !
b1110 &
1"
b11111100 #
b1111110001110011110011000000111 %
#215
0"
#220
b1111 !
b1111 &
1"
b11010110 #
b11101011000100101000111010011100 %
#225
0"
#230
b10000 !
b10000 &
1"
b1111011 #
b10111101101101100001111011101101 %
#235
0"
#240
b10001 !
b10001 &
1"
b10010010 #
b1001001010101011100110011001010 %
#245
0"
#250
b10010 !
b10010 &
1"
b11000011 #
b11100001111001010011111111000011 %
#255
0"
#260
b10011 !
b10011 &
1"
b10010001 #
b11001000100100111111011000101000 %
#265
0"
#270
b10100 !
b10100 &
1"
b110000 #
b11000001001000010011000001001 %
#275
0"
#280
b10101 !
b10101 &
1"
b10100001 #
b1010000111010011110101000110110 %
#285
0"
#290
b10110 !
b10110 &
1"
b101100 #
b10010110011010110100101100111111 %
#295
0"
#300
b10111 !
b10111 &
1"
b1100011 #
b110001111111000111010001110100 %
#305
0"
#310
b11000 !
b11000 &
1"
b10011011 #
b1001101100001110010010011100101 %
#315
0"
#320
b11001 !
b11001 &
1"
b101101 #
b10110111111010010110001100010 %
#325
0"
#330
b11010 !
b11010 &
1"
b11100000 #
b1110000010111111000010001111011 %
#335
0"
#340
b11011 !
b11011 &
1"
b10110101 #
b1011010101100100101010110000000 %
#345
0"
#350
b11100 !
b11100 &
1"
b1001 #
b100101001011111011110000001 %
#355
0"
#360
b11101 !
b11101 &
1"
b111011 #
b11101111110011011111101001110 %
#365
0"
#370
b11110 !
b11110 &
1"
b11011110 #
b1101111000000110010011101110111 %
#375
0"
#380
b11111 !
b11111 &
1"
b1101011 #
b110101111111101010010101001100 %
#385
0"
#390
b100000 !
b100000 &
1"
b10100001 #
b11010000100110110011100111011101 %
#395
0"
#400
b100001 !
b100001 &
1"
b101000000110101000111011111010 %
